riscvsingle.v
module testbench();

  reg clk;
  reg reset;

  wire [31:0] WriteData, DataAdr;
  wire MemWrite;

  top dut(clk, reset, WriteData, DataAdr, MemWrite);
  
  initial begin
    reset <= 1; #22; reset <= 0;
  end

  always begin
    clk <= 1; #5; clk <= 0; #5;
  end

  always @(negedge clk) begin
    if (MemWrite) begin
      if (DataAdr === 100 && WriteData === 25) begin
        $display("Simulation succeeded");
        $stop;
      end else if (DataAdr !== 96) begin
        $display("Simulation failed");
        $stop;
      end
    end
  end

  initial begin
  $dumpfile("dump.vcd");
  $dumpvars(0, testbench);
  end
endmodule

module top(
  input wire clk,
  input wire reset,
  output wire [31:0] WriteData,
  output wire [31:0] DataAdr,
  output wire MemWrite
);

  wire [31:0] PC, Instr, ReadData;

  riscvsingle rvsingle(
    clk, reset, PC, Instr, MemWrite, DataAdr,
    WriteData, ReadData
  );

  imem imem(PC, Instr);
  dmem dmem(clk, MemWrite, DataAdr, WriteData, ReadData);

endmodule

module riscvsingle(
  input wire clk, reset,
  output wire [31:0] PC,
  input wire [31:0] Instr,
  output wire MemWrite,
  output wire [31:0] ALUResult, WriteData,
  input wire [31:0] ReadData
);

  wire ALUSrc, RegWrite, Jump, Zero;
  wire [1:0] ResultSrc, ImmSrc;
  wire [2:0] ALUControl;
  wire PCSrc;

  controller c(
    Instr[6:0], Instr[14:12], Instr[30], Zero,
    ResultSrc, MemWrite, PCSrc,
    ALUSrc, RegWrite, Jump,
    ImmSrc, ALUControl
  );

  datapath dp(
    clk, reset, ResultSrc, PCSrc,
    ALUSrc, RegWrite,
    ImmSrc, ALUControl,
    Zero, PC, Instr,
    ALUResult, WriteData, ReadData
  );
endmodule

module controller(
  input wire [6:0] op,
  input wire [2:0] funct3,
  input wire funct7b5,
  input wire Zero,
  output wire [1:0] ResultSrc,
  output wire MemWrite,
  output wire PCSrc, ALUSrc,
  output wire RegWrite, Jump,
  output wire [1:0] ImmSrc,
  output wire [2:0] ALUControl
);

  wire [1:0] ALUOp;
  wire Branch;

  maindec md(
    op, ResultSrc, MemWrite, Branch,
    ALUSrc, RegWrite, Jump, ImmSrc, ALUOp
  );

  aludec ad(op[5], funct3, funct7b5, ALUOp, ALUControl);

  assign PCSrc = (Branch & Zero) | Jump;

endmodule

// Decodificador principal, gera sinais de controle com base no opcode
module maindec(
  input wire [6:0] op,
  output reg [1:0] ResultSrc,
  output reg MemWrite,
  output reg Branch, ALUSrc,
  output reg RegWrite, Jump,
  output reg [1:0] ImmSrc,
  output reg [1:0] ALUOp
);

  reg [10:0] controls;

  always @(*) begin
    case (op)
      7'b0000011: controls = 11'b1_00_1_0_01_0_00_0; // lw
      7'b0100011: controls = 11'b0_01_1_1_00_0_00_0; // sw
      7'b0110011: controls = 11'b1_00_0_0_00_0_10_0; // R-type
      7'b1100011: controls = 11'b0_10_0_0_00_1_01_0; // beq
      7'b0010011: controls = 11'b1_00_1_0_00_0_10_0; // I-type
      7'b1101111: controls = 11'b1_11_0_0_10_0_00_1; // jal
      default:    controls = 11'b0_00_0_0_00_0_00_0;
    endcase
  end

  always @(*) begin
    {RegWrite, ImmSrc, ALUSrc, MemWrite,
     ResultSrc, Branch, ALUOp, Jump} = controls;
  end

endmodule

// Decodificador ALU, gera sinais de controle ALU com base em funct3, funct7 e ALUOp
module aludec(
  input wire opb5,
  input wire [2:0] funct3,
  input wire funct7b5,
  input wire [1:0] ALUOp,
  output reg [2:0] ALUControl
);

  wire RtypeSub;
  assign RtypeSub = funct7b5 & opb5;

  always @(*) begin
    case (ALUOp)
      2'b00: ALUControl = 3'b000;
      2'b01: ALUControl = 3'b001;
      default:
        case (funct3)
          3'b000: ALUControl = RtypeSub ? 3'b001 : 3'b000;
          3'b010: ALUControl = 3'b101;
          3'b110: ALUControl = 3'b011;
          3'b111: ALUControl = 3'b010;
          default: ALUControl = 3'b000;
        endcase
    endcase
  end
endmodule

module datapath(
  input wire clk, reset,
  input wire [1:0] ResultSrc,
  input wire PCSrc, ALUSrc,
  input wire RegWrite,
  input wire [1:0] ImmSrc,
  input wire [2:0] ALUControl,
  output wire Zero,
  output wire [31:0] PC,
  input wire [31:0] Instr,
  output wire [31:0] ALUResult, WriteData,
  input wire [31:0] ReadData
);

  wire [31:0] PCNext, PCPlus4, PCTarget;
  wire [31:0] ImmExt;
  wire [31:0] SrcA, SrcB;
  wire [31:0] Result;

  flopr #(32) pcreg(clk, reset, PCNext, PC);
  adder pcadd4(PC, 32'd4, PCPlus4);
  adder pcaddbranch(PC, ImmExt, PCTarget);

  mux2 #(32) pcmux(PCPlus4, PCTarget, PCSrc, PCNext);

  regfile rf(
    clk, RegWrite, Instr[19:15], Instr[24:20],
    Instr[11:7], Result, SrcA, WriteData
  );

  extend ext(Instr[31:7], ImmSrc, ImmExt);

  mux2 #(32) srcbmux(WriteData, ImmExt, ALUSrc, SrcB);

  alu alu(SrcA, SrcB, ALUControl, ALUResult, Zero);

  mux3 #(32) resultmux(ALUResult, ReadData, PCPlus4, ResultSrc, Result);

endmodule

// Banco de registradores
module regfile(
  input wire clk,
  input wire we3,
  input wire [4:0] a1, a2, a3,
  input wire [31:0] wd3,
  output wire [31:0] rd1, rd2
);

  reg [31:0] rf[31:0];

  always @(posedge clk)
    if (we3) rf[a3] <= wd3;

  assign rd1 = (a1 != 0) ? rf[a1] : 32'b0;
  assign rd2 = (a2 != 0) ? rf[a2] : 32'b0;

endmodule

module adder(
  input wire [31:0] a, b, 
  output wire [31:0] y
);
  assign y = a + b;
endmodule

// Extensor de imediato
module extend(
  input wire [31:7] instr,
  input wire [1:0] immsrc,
  output reg [31:0] immext
);

  always @(*) begin
    case (immsrc)
      2'b00: immext = {{20{instr[31]}}, instr[31:20]};
      2'b01: immext = {{20{instr[31]}}, instr[31:25], instr[11:7]};
      2'b10: immext = {{20{instr[31]}}, instr[7], instr[30:25], instr[11:8], 1'b0};
      2'b11: immext = {{12{instr[31]}}, instr[19:12], instr[20], instr[30:21], 1'b0};
      default: immext = 32'b0;
    endcase
  end

endmodule

// Flip-flop com reset síncrono
module flopr #(parameter WIDTH = 8)(
  input wire clk, reset,
  input wire [WIDTH-1:0] d,
  output reg [WIDTH-1:0] q
);

  always @(posedge clk or posedge reset)
    if (reset) q <= 0;
    else       q <= d;

endmodule

// Multiplexador de 2 para 1
module mux2 #(parameter WIDTH = 8)(
  input wire [WIDTH-1:0] d0, d1,
  input wire s,
  output wire [WIDTH-1:0] y
);
  assign y = s ? d1 : d0;
endmodule

// Multiplexador de 3 para 1
module mux3 #(parameter WIDTH = 8)(
  input wire [WIDTH-1:0] d0, d1, d2,
  input wire [1:0] s,
  output wire [WIDTH-1:0] y
);
  assign y = s[1] ? d2 : (s[0] ? d1 : d0);
endmodule


// Unidade Lógica e Aritmética (ALU)
module alu(
  input wire [31:0] a, b,
  input wire [2:0] alucontrol,
  output reg [31:0] result,
  output wire zero
);

  wire [31:0] condinvb, sum;
  wire v;
  wire isAddSub;

  assign condinvb = alucontrol[0] ? ~b : b;
  assign sum = a + condinvb + alucontrol[0];

  assign isAddSub = (~alucontrol[2] & ~alucontrol[1]) |
                    (~alucontrol[1] & alucontrol[0]);

  always @(*) begin
    case (alucontrol)
      3'b000: result = sum;
      3'b001: result = sum;
      3'b010: result = a & b;
      3'b011: result = a | b;
      3'b100: result = a ^ b;
      3'b101: result = sum[31] ^ v;
      3'b110: result = a << b[4:0];
      3'b111: result = a >> b[4:0];
      default: result = 32'b0;
    endcase
  end

  assign zero = (result == 0);

  assign v = ~(alucontrol[0] ^ a[31] ^ b[31]) &
             (a[31] ^ sum[31]) & isAddSub;

endmodule

// Memória de instruções
module imem(input wire [31:0] a, output wire [31:0] rd);

  reg [31:0] RAM[63:0];

  initial begin
    $readmemh("riscvtest.txt", RAM);
  end

  assign rd = RAM[a[31:2]];

endmodule

// Memória de dados
module dmem(
  input wire clk, we,
  input wire [31:0] a, wd,
  output wire [31:0] rd
);

  reg [31:0] RAM[63:0];

  assign rd = RAM[a[31:2]];

  always @(posedge clk)
    if (we) RAM[a[31:2]] <= wd;

endmodule

dump.vcd
$date
	Mon Dec 08 23:31:54 2025
$end
$version
	Icarus Verilog
$end
$timescale
	1s
$end
$scope module testbench $end
$var wire 32 ! WriteData [31:0] $end
$var wire 1 " MemWrite $end
$var wire 32 # DataAdr [31:0] $end
$var reg 1 $ clk $end
$var reg 1 % reset $end
$scope module dut $end
$var wire 1 $ clk $end
$var wire 1 % reset $end
$var wire 32 & WriteData [31:0] $end
$var wire 32 ' ReadData [31:0] $end
$var wire 32 ( PC [31:0] $end
$var wire 1 " MemWrite $end
$var wire 32 ) Instr [31:0] $end
$var wire 32 * DataAdr [31:0] $end
$scope module dmem $end
$var wire 1 $ clk $end
$var wire 32 + rd [31:0] $end
$var wire 1 " we $end
$var wire 32 , wd [31:0] $end
$var wire 32 - a [31:0] $end
$upscope $end
$scope module imem $end
$var wire 32 . rd [31:0] $end
$var wire 32 / a [31:0] $end
$upscope $end
$scope module rvsingle $end
$var wire 32 0 Instr [31:0] $end
$var wire 32 1 ReadData [31:0] $end
$var wire 1 $ clk $end
$var wire 1 % reset $end
$var wire 1 2 Zero $end
$var wire 32 3 WriteData [31:0] $end
$var wire 2 4 ResultSrc [1:0] $end
$var wire 1 5 RegWrite $end
$var wire 1 6 PCSrc $end
$var wire 32 7 PC [31:0] $end
$var wire 1 " MemWrite $end
$var wire 1 8 Jump $end
$var wire 2 9 ImmSrc [1:0] $end
$var wire 1 : ALUSrc $end
$var wire 32 ; ALUResult [31:0] $end
$var wire 3 < ALUControl [2:0] $end
$scope module c $end
$var wire 1 6 PCSrc $end
$var wire 3 = funct3 [2:0] $end
$var wire 1 > funct7b5 $end
$var wire 7 ? op [6:0] $end
$var wire 1 2 Zero $end
$var wire 2 @ ResultSrc [1:0] $end
$var wire 1 5 RegWrite $end
$var wire 1 " MemWrite $end
$var wire 1 8 Jump $end
$var wire 2 A ImmSrc [1:0] $end
$var wire 1 B Branch $end
$var wire 1 : ALUSrc $end
$var wire 2 C ALUOp [1:0] $end
$var wire 3 D ALUControl [2:0] $end
$scope module ad $end
$var wire 1 E RtypeSub $end
$var wire 3 F funct3 [2:0] $end
$var wire 1 > funct7b5 $end
$var wire 1 G opb5 $end
$var wire 2 H ALUOp [1:0] $end
$var reg 3 I ALUControl [2:0] $end
$upscope $end
$scope module md $end
$var wire 7 J op [6:0] $end
$var reg 2 K ALUOp [1:0] $end
$var reg 1 : ALUSrc $end
$var reg 1 B Branch $end
$var reg 2 L ImmSrc [1:0] $end
$var reg 1 8 Jump $end
$var reg 1 " MemWrite $end
$var reg 1 5 RegWrite $end
$var reg 2 M ResultSrc [1:0] $end
$var reg 11 N controls [10:0] $end
$upscope $end
$upscope $end
$scope module dp $end
$var wire 3 O ALUControl [2:0] $end
$var wire 1 : ALUSrc $end
$var wire 2 P ImmSrc [1:0] $end
$var wire 32 Q Instr [31:0] $end
$var wire 1 6 PCSrc $end
$var wire 32 R ReadData [31:0] $end
$var wire 1 5 RegWrite $end
$var wire 2 S ResultSrc [1:0] $end
$var wire 1 $ clk $end
$var wire 1 % reset $end
$var wire 1 2 Zero $end
$var wire 32 T WriteData [31:0] $end
$var wire 32 U SrcB [31:0] $end
$var wire 32 V SrcA [31:0] $end
$var wire 32 W Result [31:0] $end
$var wire 32 X PCTarget [31:0] $end
$var wire 32 Y PCPlus4 [31:0] $end
$var wire 32 Z PCNext [31:0] $end
$var wire 32 [ PC [31:0] $end
$var wire 32 \ ImmExt [31:0] $end
$var wire 32 ] ALUResult [31:0] $end
$scope module alu $end
$var wire 3 ^ alucontrol [2:0] $end
$var wire 1 _ isAddSub $end
$var wire 1 ` v $end
$var wire 1 2 zero $end
$var wire 32 a sum [31:0] $end
$var wire 32 b condinvb [31:0] $end
$var wire 32 c b [31:0] $end
$var wire 32 d a [31:0] $end
$var reg 32 e result [31:0] $end
$upscope $end
$scope module ext $end
$var wire 2 f immsrc [1:0] $end
$var wire 25 g instr [31:7] $end
$var reg 32 h immext [31:0] $end
$upscope $end
$scope module pcadd4 $end
$var wire 32 i b [31:0] $end
$var wire 32 j y [31:0] $end
$var wire 32 k a [31:0] $end
$upscope $end
$scope module pcaddbranch $end
$var wire 32 l b [31:0] $end
$var wire 32 m y [31:0] $end
$var wire 32 n a [31:0] $end
$upscope $end
$scope module pcmux $end
$var wire 32 o d0 [31:0] $end
$var wire 32 p d1 [31:0] $end
$var wire 1 6 s $end
$var wire 32 q y [31:0] $end
$upscope $end
$scope module pcreg $end
$var wire 1 $ clk $end
$var wire 32 r d [31:0] $end
$var wire 1 % reset $end
$var reg 32 s q [31:0] $end
$upscope $end
$scope module resultmux $end
$var wire 32 t d0 [31:0] $end
$var wire 32 u d1 [31:0] $end
$var wire 32 v d2 [31:0] $end
$var wire 2 w s [1:0] $end
$var wire 32 x y [31:0] $end
$upscope $end
$scope module rf $end
$var wire 5 y a1 [4:0] $end
$var wire 5 z a2 [4:0] $end
$var wire 5 { a3 [4:0] $end
$var wire 1 $ clk $end
$var wire 32 | wd3 [31:0] $end
$var wire 1 5 we3 $end
$var wire 32 } rd2 [31:0] $end
$var wire 32 ~ rd1 [31:0] $end
$upscope $end
$scope module srcbmux $end
$var wire 32 !" d0 [31:0] $end
$var wire 32 "" d1 [31:0] $end
$var wire 1 : s $end
$var wire 32 #" y [31:0] $end
$upscope $end
$upscope $end
$upscope $end
$upscope $end
$upscope $end
$enddefinitions $end
#0
$dumpvars
b101 #"
b101 ""
bx !"
b0 ~
bx }
b101 |
b10 {
b101 z
b0 y
b101 x
b0 w
b100 v
bx u
b101 t
b0 s
b100 r
b100 q
b101 p
b100 o
b0 n
b101 m
b101 l
b0 k
b100 j
b100 i
b101 h
b1010000000000010 g
b0 f
b101 e
b0 d
b101 c
b101 b
b101 a
0`
1_
b0 ^
b101 ]
b101 \
b0 [
b100 Z
b100 Y
b101 X
b101 W
b0 V
b101 U
bx T
b0 S
bx R
b10100000000000100010011 Q
b0 P
b0 O
b10010000100 N
b0 M
b0 L
b10 K
b10011 J
b0 I
b10 H
0G
b0 F
0E
b0 D
b10 C
0B
b0 A
b0 @
b10011 ?
0>
b0 =
b0 <
b101 ;
1:
b0 9
08
b0 7
06
15
b0 4
bx 3
02
bx 1
b10100000000000100010011 0
b0 /
b10100000000000100010011 .
b101 -
bx ,
bx +
b101 *
b10100000000000100010011 )
b0 (
bx '
bx &
1%
1$
b101 #
0"
bx !
$end
#5
0$
#10
1$
#15
0$
#20
1$
#22
0%
#25
0$
#30
b1100 W
b1100 x
b1100 |
b1100 #
b1100 *
b1100 -
b1100 ;
b1100 ]
b1100 e
b1100 t
b1100 a
b1100 b
b1100 U
b1100 c
b1100 #"
b1100 \
b1100 h
b1100 l
b1100 ""
b1100 z
b11 {
b11000000000000011 g
b1000 Z
b1000 q
b1000 r
b110000000000000110010011 )
b110000000000000110010011 .
b110000000000000110010011 0
b110000000000000110010011 Q
b10000 X
b10000 m
b10000 p
b1000 Y
b1000 j
b1000 o
b1000 v
b100 (
b100 /
b100 7
b100 [
b100 k
b100 n
b100 s
1$
#35
0$
#40
b11 W
b11 x
b11 |
b11111111111111111111111111110111 b
b11 #
b11 *
b11 -
b11 ;
b11 ]
b11 e
b11 t
b11111111111111111111111111110111 U
b11111111111111111111111111110111 c
b11111111111111111111111111110111 #"
b11 a
b1100 V
b1100 d
b1100 ~
b11111111111111111111111111110111 \
b11111111111111111111111111110111 h
b11111111111111111111111111110111 l
b11111111111111111111111111110111 ""
1>
b11 y
b10111 z
b111 {
b1111111101110001100000111 g
b1100 Z
b1100 q
b1100 r
b11111111011100011000001110010011 )
b11111111011100011000001110010011 .
b11111111011100011000001110010011 0
b11111111011100011000001110010011 Q
b11111111111111111111111111111111 X
b11111111111111111111111111111111 m
b11111111111111111111111111111111 p
b1100 Y
b1100 j
b1100 o
b1100 v
b1000 (
b1000 /
b1000 7
b1000 [
b1000 k
b1000 n
b1000 s
1$
#45
0$
#50
b111 W
b111 x
b111 |
0_
b111 #
b111 *
b111 -
b111 ;
b111 ]
b111 e
b111 t
b11111111111111111111111111111010 b
0:
b101 U
b101 c
b101 #"
1G
b10000000100 N
b11 <
b11 D
b11 I
b11 O
b11 ^
b11111111111111111111111111111110 a
b11 V
b11 d
b11 ~
b101 !
b101 &
b101 ,
b101 3
b101 T
b101 }
b101 !"
b10 \
b10 h
b10 l
b10 ""
b110011 ?
b110011 J
b110 =
b110 F
0>
b111 y
b10 z
b100 {
b100011111000100 g
b10000 Z
b10000 q
b10000 r
b1000111110001000110011 )
b1000111110001000110011 .
b1000111110001000110011 0
b1000111110001000110011 Q
b1110 X
b1110 m
b1110 p
b10000 Y
b10000 j
b10000 o
b10000 v
b1100 (
b1100 /
b1100 7
b1100 [
b1100 k
b1100 n
b1100 s
1$
#55
0$
#60
b100 W
b100 x
b100 |
b111 b
b100 #
b100 *
b100 -
b100 ;
b100 ]
b100 e
b100 t
b111 U
b111 c
b111 #"
b10 <
b10 D
b10 I
b10 O
b10 ^
b10011 a
b1100 V
b1100 d
b1100 ~
b111 !
b111 &
b111 ,
b111 3
b111 T
b111 }
b111 !"
b100 \
b100 h
b100 l
b100 ""
b111 =
b111 F
b11 y
b100 z
b101 {
b1000001111100101 g
b10100 Z
b10100 q
b10100 r
b10000011111001010110011 )
b10000011111001010110011 .
b10000011111001010110011 0
b10000011111001010110011 Q
b10100 X
b10100 m
b10100 p
b10100 Y
b10100 j
b10100 o
b10100 v
b10000 (
b10000 /
b10000 7
b10000 [
b10000 k
b10000 n
b10000 s
1$
#65
0$
#70
1_
b1011 W
b1011 x
b1011 |
b1011 #
b1011 *
b1011 -
b1011 ;
b1011 ]
b1011 e
b1011 t
b0 <
b0 D
b0 I
b0 O
b0 ^
b1011 a
b100 V
b100 d
b100 ~
b0 =
b0 F
b101 y
b1000010100000101 g
b11000 Z
b11000 q
b11000 r
b10000101000001010110011 )
b10000101000001010110011 .
b10000101000001010110011 0
b10000101000001010110011 Q
b11000 X
b11000 m
b11000 p
b11000 Y
b11000 j
b11000 o
b11000 v
b10100 (
b10100 /
b10100 7
b10100 [
b10100 k
b10100 n
b10100 s
1$
#75
0$
#80
b1 <
b1 D
b1 I
b1 O
b1 ^
b11111111111111111111111111111100 b
b1000 W
b1000 x
b1000 |
05
b10 9
b10 A
b10 L
b10 P
b10 f
1B
b1 C
b1 H
b1 K
b11 U
b11 c
b11 #"
b1000001010 N
b11 !
b11 &
b11 ,
b11 3
b11 T
b11 }
b11 !"
b110000 \
b110000 h
b110000 l
b110000 ""
b1000 #
b1000 *
b1000 -
b1000 ;
b1000 ]
b1000 e
b1000 t
b1100011 ?
b1100011 J
b111 z
b10000 {
b1001110010100010000 g
b1000 a
b1011 V
b1011 d
b1011 ~
b11100 Z
b11100 q
b11100 r
b10011100101000100001100011 )
b10011100101000100001100011 .
b10011100101000100001100011 0
b10011100101000100001100011 Q
b1001000 X
b1001000 m
b1001000 p
b11100 Y
b11100 j
b11100 o
b11100 v
b11000 (
b11000 /
b11000 7
b11000 [
b11000 k
b11000 n
b11000 s
1$
#85
0$
#90
12
b0 W
b0 x
b0 |
b11111111111111111111111111111000 b
b101 <
b101 D
b101 I
b101 O
b101 ^
15
b0 9
b0 A
b0 L
b0 P
b0 f
0B
b10 C
b10 H
b10 K
b0 #
b0 *
b0 -
b0 ;
b0 ]
b0 e
b0 t
b111 U
b111 c
b111 #"
b10000000100 N
b101 a
b1100 V
b1100 d
b1100 ~
b111 !
b111 &
b111 ,
b111 3
b111 T
b111 }
b111 !"
b100 \
b100 h
b100 l
b100 ""
b110011 ?
b110011 J
b10 =
b10 F
b11 y
b100 z
b100 {
b1000001101000100 g
b100000 Z
b100000 q
b100000 r
b10000011010001000110011 )
b10000011010001000110011 .
b10000011010001000110011 0
b10000011010001000110011 Q
b100000 X
b100000 m
b100000 p
b100000 Y
b100000 j
b100000 o
b100000 v
b11100 (
b11100 /
b11100 7
b11100 [
b11100 k
b11100 n
b11100 s
1$
#95
0$
#100
16
1_
b0 W
b0 x
b0 |
b11111111111111111111111111111111 b
05
b10 9
b10 A
b10 L
b10 P
b10 f
1B
b1 C
b1 H
b1 K
12
b0 #
b0 *
b0 -
b0 ;
b0 ]
b0 e
b0 t
b1000001010 N
b1 <
b1 D
b1 I
b1 O
b1 ^
b0 a
b0 V
b0 d
b0 ~
b1000 \
b1000 h
b1000 l
b1000 ""
b0 U
b0 c
b0 #"
b1100011 ?
b1100011 J
b0 =
b0 F
b100 y
b0 z
b1000 {
b10000001000 g
b0 !
b0 &
b0 ,
b0 3
b0 T
b0 }
b0 !"
b101000 Z
b101000 q
b101000 r
b100000010001100011 )
b100000010001100011 .
b100000010001100011 0
b100000010001100011 Q
b101000 X
b101000 m
b101000 p
b100100 Y
b100100 j
b100100 o
b100100 v
b100000 (
b100000 /
b100000 7
b100000 [
b100000 k
b100000 n
b100000 s
1$
#105
0$
#110
06
b1 W
b1 x
b1 |
b11111111111111111111111111111010 b
b101 <
b101 D
b101 I
b101 O
b101 ^
15
b0 9
b0 A
b0 L
b0 P
b0 f
0B
b10 C
b10 H
b10 K
02
b1 #
b1 *
b1 -
b1 ;
b1 ]
b1 e
b1 t
b101 U
b101 c
b101 #"
b10000000100 N
b11111111111111111111111111111110 a
b11 V
b11 d
b11 ~
b101 !
b101 &
b101 ,
b101 3
b101 T
b101 }
b101 !"
b10 \
b10 h
b10 l
b10 ""
b110011 ?
b110011 J
b10 =
b10 F
b111 y
b10 z
b100 {
b100011101000100 g
b101100 Z
b101100 q
b101100 r
b1000111010001000110011 )
b1000111010001000110011 .
b1000111010001000110011 0
b1000111010001000110011 Q
b101010 X
b101010 m
b101010 p
b101100 Y
b101100 j
b101100 o
b101100 v
b101000 (
b101000 /
b101000 7
b101000 [
b101000 k
b101000 n
b101000 s
1$
#115
0$
#120
1_
b1100 W
b1100 x
b1100 |
b1011 b
b1100 #
b1100 *
b1100 -
b1100 ;
b1100 ]
b1100 e
b1100 t
b1011 U
b1011 c
b1011 #"
b0 <
b0 D
b0 I
b0 O
b0 ^
b1100 a
b1 V
b1 d
b1 ~
b1011 !
b1011 &
b1011 ,
b1011 3
b1011 T
b1011 }
b1011 !"
b101 \
b101 h
b101 l
b101 ""
b0 =
b0 F
b100 y
b101 z
b111 {
b1010010000000111 g
b110000 Z
b110000 q
b110000 r
b10100100000001110110011 )
b10100100000001110110011 .
b10100100000001110110011 0
b10100100000001110110011 Q
b110001 X
b110001 m
b110001 p
b110000 Y
b110000 j
b110000 o
b110000 v
b101100 (
b101100 /
b101100 7
b101100 [
b101100 k
b101100 n
b101100 s
1$
#125
0$
#130
b111 W
b111 x
b111 |
b11111111111111111111111111111010 b
b1 <
b1 D
b1 I
b1 O
b1 ^
b111 #
b111 *
b111 -
b111 ;
b111 ]
b111 e
b111 t
b101 U
b101 c
b101 #"
1E
b111 a
b1100 V
b1100 d
b1100 ~
b101 !
b101 &
b101 ,
b101 3
b101 T
b101 }
b101 !"
b10000000010 \
b10000000010 h
b10000000010 l
b10000000010 ""
1>
b111 y
b10 z
b100000000100011100000111 g
b110100 Z
b110100 q
b110100 r
b1000000001000111000001110110011 )
b1000000001000111000001110110011 .
b1000000001000111000001110110011 0
b1000000001000111000001110110011 Q
b10000110010 X
b10000110010 m
b10000110010 p
b110100 Y
b110100 j
b110100 o
b110100 v
b110000 (
b110000 /
b110000 7
b110000 [
b110000 k
b110000 n
b110000 s
1$
#135
0$
#140
1_
b1010100 b
b1100000 W
b1100000 x
b1100000 |
05
b1 9
b1 A
b1 L
b1 P
b1 f
1:
1"
b0 C
b0 H
b0 K
02
b1010100 U
b1010100 c
b1010100 #"
b111000000 N
b0 <
b0 D
b0 I
b0 O
b0 ^
0E
b111 !
b111 &
b111 ,
b111 3
b111 T
b111 }
b111 !"
b1010100 \
b1010100 h
b1010100 l
b1010100 ""
b1100000 #
b1100000 *
b1100000 -
b1100000 ;
b1100000 ]
b1100000 e
b1100000 t
b100011 ?
b100011 J
b10 =
b10 F
0>
b11 y
b111 z
b10100 {
b10001110001101010100 g
b1100000 a
b1100 V
b1100 d
b1100 ~
b111000 Z
b111000 q
b111000 r
b100011100011010101000100011 )
b100011100011010101000100011 .
b100011100011010101000100011 0
b100011100011010101000100011 Q
b10001000 X
b10001000 m
b10001000 p
b111000 Y
b111000 j
b111000 o
b111000 v
b110100 (
b110100 /
b110100 7
b110100 [
b110100 k
b110100 n
b110100 s
1$
#145
0$
#150
b111 W
b111 x
b111 |
b1100000 b
15
b0 9
b0 A
b0 L
b0 P
b0 f
0"
b1 4
b1 @
b1 M
b1 S
b1 w
b1100000 #
b1100000 *
b1100000 -
b1100000 ;
b1100000 ]
b1100000 e
b1100000 t
b1100000 U
b1100000 c
b1100000 #"
0G
b10010010000 N
b1100000 a
b0 V
b0 d
b0 ~
b0 !
b0 &
b0 ,
b0 3
b0 T
b0 }
b0 !"
b1100000 \
b1100000 h
b1100000 l
b1100000 ""
b11 ?
b11 J
b0 y
b0 z
b10 {
b11000000000001000010 g
b111100 Z
b111100 q
b111100 r
b110000000000010000100000011 )
b110000000000010000100000011 .
b110000000000010000100000011 0
b110000000000010000100000011 Q
b111 '
b111 +
b111 1
b111 R
b111 u
b10011000 X
b10011000 m
b10011000 p
b111100 Y
b111100 j
b111100 o
b111100 v
b111000 (
b111000 /
b111000 7
b111000 [
b111000 k
b111000 n
b111000 s
1$
#155
0$
#160
b10010 W
b10010 x
b10010 |
bx '
bx +
bx 1
bx R
bx u
b1011 b
0:
b0 4
b0 @
b0 M
b0 S
b0 w
b10 C
b10 H
b10 K
b10010 #
b10010 *
b10010 -
b10010 ;
b10010 ]
b10010 e
b10010 t
b1011 U
b1011 c
b1011 #"
1G
b10000000100 N
b10010 a
b111 V
b111 d
b111 ~
b1011 !
b1011 &
b1011 ,
b1011 3
b1011 T
b1011 }
b1011 !"
b101 \
b101 h
b101 l
b101 ""
b110011 ?
b110011 J
b0 =
b0 F
b10 y
b101 z
b1001 {
b1010001000001001 g
b1000000 Z
b1000000 q
b1000000 r
b10100010000010010110011 )
b10100010000010010110011 .
b10100010000010010110011 0
b10100010000010010110011 Q
b1000001 X
b1000001 m
b1000001 p
b1000000 Y
b1000000 j
b1000000 o
b1000000 v
b111100 (
b111100 /
b111100 7
b111100 [
b111100 k
b111100 n
b111100 s
1$
#165
0$
#170
x`
b1000100 W
b1000100 x
b1000100 |
x2
16
bx b
b11 9
b11 A
b11 L
b11 P
b11 f
b10 4
b10 @
b10 M
b10 S
b10 w
b0 C
b0 H
b0 K
18
bx #
bx *
bx -
bx ;
bx ]
bx e
bx t
bx U
bx c
bx #"
b11100100001 N
bx a
b0 V
b0 d
b0 ~
bx !
bx &
bx ,
bx 3
bx T
bx }
bx !"
b1000 \
b1000 h
b1000 l
b1000 ""
b1101111 ?
b1101111 J
b0 y
b1000 z
b11 {
b10000000000000011 g
b1001000 Z
b1001000 q
b1001000 r
b100000000000000111101111 )
b100000000000000111101111 .
b100000000000000111101111 0
b100000000000000111101111 Q
b1001000 X
b1001000 m
b1001000 p
b1000100 Y
b1000100 j
b1000100 o
b1000100 v
b1000000 (
b1000000 /
b1000000 7
b1000000 [
b1000000 k
b1000000 n
b1000000 s
1$
#175
0$
#180
0`
02
b11001 #
b11001 *
b11001 -
b11001 ;
b11001 ]
b11001 e
b11001 t
06
b11001 a
b10010 b
b0 9
b0 A
b0 L
b0 P
b0 f
b0 4
b0 @
b0 M
b0 S
b0 w
b10 C
b10 H
b10 K
08
b10010 U
b10010 c
b10010 #"
b10000000100 N
b111 V
b111 d
b111 ~
b10010 !
b10010 &
b10010 ,
b10010 3
b10010 T
b10010 }
b10010 !"
b1001 \
b1001 h
b1001 l
b1001 ""
b110011 ?
b110011 J
b10 y
b1001 z
b10 {
b10010001000000010 g
b1001100 Z
b1001100 q
b1001100 r
b11001 W
b11001 x
b11001 |
b100100010000000100110011 )
b100100010000000100110011 .
b100100010000000100110011 0
b100100010000000100110011 Q
b1010001 X
b1010001 m
b1010001 p
b1001100 Y
b1001100 j
b1001100 o
b1001100 v
b1001000 (
b1001000 /
b1001000 7
b1001000 [
b1001000 k
b1001000 n
b1001000 s
1$
#185
0$
#190
1_
b100000 b
b1100100 W
b1100100 x
b1100100 |
05
b1 9
b1 A
b1 L
b1 P
b1 f
1:
1"
b0 C
b0 H
b0 K
02
b100000 U
b100000 c
b100000 #"
b111000000 N
b0 <
b0 D
b0 I
b0 O
b0 ^
b11001 !
b11001 &
b11001 ,
b11001 3
b11001 T
b11001 }
b11001 !"
b100000 \
b100000 h
b100000 l
b100000 ""
b1100100 #
b1100100 *
b1100100 -
b1100100 ;
b1100100 ]
b1100100 e
b1100100 t
b100011 ?
b100011 J
b10 =
b10 F
b11 y
b10 z
b0 {
b1000100001101000000 g
b1100100 a
b1000100 V
b1000100 d
b1000100 ~
b1010000 Z
b1010000 q
b1010000 r
b10001000011010000000100011 )
b10001000011010000000100011 .
b10001000011010000000100011 0
b10001000011010000000100011 Q
b1101100 X
b1101100 m
b1101100 p
b1010000 Y
b1010000 j
b1010000 o
b1010000 v
b1001100 (
b1001100 /
b1001100 7
b1001100 [
b1001100 k
b1001100 n
b1001100 s
1$
